pyxll_jupyter/__init__.py
pyxll_jupyter/kernel.py
pyxll_jupyter/magic.py
pyxll_jupyter/onedrive.py
pyxll_jupyter/kernel_managers/__init__.py
pyxll_jupyter/kernel_managers/extipy.py
pyxll_jupyter/kernel_managers/labkm.py
pyxll_jupyter/kernel_managers/nbkm.py
pyxll_jupyter/provisioning/__init__.py
pyxll_jupyter/provisioning/existing.py
pyxll_jupyter/pyxll/__init__.py
pyxll_jupyter/pyxll/impl.py
pyxll_jupyter/resources/__init__.py
pyxll_jupyter/resources/browser.png
pyxll_jupyter/resources/jupyter.png
pyxll_jupyter/resources/ribbon.xml
pyxll_jupyter/widgets/__init__.py
pyxll_jupyter/widgets/browser.py
pyxll_jupyter/widgets/jupyter.py
pyxll_jupyter/widgets/qtimports.py
pyxll_jupyter-0.6.2.dist-info/licenses/LICENSE.md
pyxll_jupyter-0.6.2.dist-info/METADATA
pyxll_jupyter-0.6.2.dist-info/WHEEL
pyxll_jupyter-0.6.2.dist-info/entry_points.txt
pyxll_jupyter-0.6.2.dist-info/top_level.txt
pyxll_jupyter-0.6.2.dist-info/RECORD
