Metadata-Version: 2.4
Name: pyxll_jupyter
Version: 0.6.2
Summary: Adds Jupyter notebooks to Microsoft Excel using PyXLL.
Author-email: Tony Roberts <tony@pyxll.com>
License-Expression: MIT
Project-URL: Repository, https://github.com/pyxll/pyxll-jupyter
Project-URL: Issues, https://github.com/pyxll/pyxll-jupyter/issues
Classifier: Programming Language :: Python :: 3
Classifier: Operating System :: Microsoft :: Windows
License-File: LICENSE.md
Requires-Dist: pyxll>=5.1.0
Requires-Dist: jupyter>=1.0.0
Requires-Dist: jupyter-client>=6.0.0
Requires-Dist: notebook>=6.0.0
Requires-Dist: packaging; python_version >= "3.10"
Requires-Dist: PySide2; python_version < "3.10"
Requires-Dist: PySide6!=6.4.2; python_version >= "3.10" and platform_machine == "x86_64"
Requires-Dist: PyQt5; python_version >= "3.10" and platform_machine != "x86_64"
Requires-Dist: PyQtWebEngine; python_version >= "3.10" and platform_machine != "x86_64"
Dynamic: license-file
